kini/__init__.py
kini/__main__.py
kini/mascot.py
kini/password_manager.py
kini-1.0.0.dist-info/licenses/LICENSE
tests/__init__.py
tests/conftest.py
tests/test_password_manager.py
kini-1.0.0.dist-info/METADATA
kini-1.0.0.dist-info/WHEEL
kini-1.0.0.dist-info/entry_points.txt
kini-1.0.0.dist-info/top_level.txt
kini-1.0.0.dist-info/RECORD
